{"version":{"pluginId":"default","version":"current","label":"Next","banner":null,"badge":false,"noIndex":false,"className":"docs-version-current","isLast":true,"docsSidebars":{"tutorialSidebar":[{"type":"link","label":"Overview","href":"/","docId":"index","unlisted":false},{"type":"category","label":"Human Behavior Patterns","items":[{"type":"category","label":"Fundamentals","items":[{"type":"link","label":"Domains","href":"/fundamentals/domains","docId":"fundamentals/domains","unlisted":false}],"collapsed":true,"collapsible":true,"href":"/fundamentals"},{"type":"link","label":"The Workings","href":"/brain","docId":"brain","unlisted":false}],"collapsed":true,"collapsible":true,"href":"/human-behavior-patterns-overview"}]},"docs":{"brain":{"id":"brain","title":"The Workings","description":"The Brain and Behavior – How does it work?","sidebar":"tutorialSidebar"},"fundamentals":{"id":"fundamentals","title":"Fundamentals of Behavior","description":"Which fundamentals do generate human behavior?","sidebar":"tutorialSidebar"},"fundamentals/domains":{"id":"fundamentals/domains","title":"Fundamentals per domain","description":"A closer look into the origins of behavior","sidebar":"tutorialSidebar"},"human-behavior-patterns-overview":{"id":"human-behavior-patterns-overview","title":"Human Behavior Patterns","description":"This project aims to model general human behavior patterns. This modeling of human behavior is meant to be descriptive, rather than prescriptive. Furthermore we aim to integrate state-of-the-art Artificial Intelligence concepts into into modeling human behavior patterns, notably from multi agent reinforcement learning (MARL) and Artificial Life Intelligence.","sidebar":"tutorialSidebar"},"index":{"id":"index","title":"Human Behavior Patterns","description":"This project aims to model general human behavior patterns. This modeling of human behavior is meant to be descriptive, rather than prescriptive. Furthermore we aim to integrate state-of-the-art Artificial Intelligence concepts into into modeling human behavior patterns, notably from multi agent reinforcement learning (MARL) and Artificial Life Intelligence.","sidebar":"tutorialSidebar"}}}}